CHANGES
LICENSE
m2secret.py
setup.cfg
setup.py
m2secret.egg-info/PKG-INFO
m2secret.egg-info/SOURCES.txt
m2secret.egg-info/dependency_links.txt
m2secret.egg-info/entry_points.txt
m2secret.egg-info/requires.txt
m2secret.egg-info/top_level.txt
m2secret.egg-info/zip-safe